irisml/tasks/call_azure_openai_completion.py
irisml/tasks/compute_image_token_number.py
irisml/tasks/compute_text_token_number.py
irisml/tasks/create_azure_openai_chat_model.py
irisml/tasks/create_azure_openai_chat_with_images_model.py
irisml/tasks/create_azure_openai_completion_model.py
irisml/tasks/extract_azure_openai_predictions.py
irisml_tasks_azure_openai-0.0.17.dist-info/licenses/LICENSE
irisml_tasks_azure_openai-0.0.17.dist-info/METADATA
irisml_tasks_azure_openai-0.0.17.dist-info/WHEEL
irisml_tasks_azure_openai-0.0.17.dist-info/top_level.txt
irisml_tasks_azure_openai-0.0.17.dist-info/RECORD
