Metadata-Version: 2.4
Name: irisml-tasks-azure-openai
Version: 0.0.17
Summary: Azure OpenAI tasks for IrisML
Home-page: https://github.com/microsoft/irisml-tasks-azure-openai
Author: irisdev
License: MIT
Requires-Python: >=3.8
License-File: LICENSE
Requires-Dist: irisml
Requires-Dist: Pillow
Requires-Dist: requests
Requires-Dist: tenacity
Requires-Dist: tiktoken
Requires-Dist: torchvision
Dynamic: license-file
